dataextractors/__init__.py
dataextractors/dataextractors.py
dataextractors-0.1.0.dist-info/DESCRIPTION.rst
dataextractors-0.1.0.dist-info/METADATA
dataextractors-0.1.0.dist-info/RECORD
dataextractors-0.1.0.dist-info/WHEEL
dataextractors-0.1.0.dist-info/metadata.json
dataextractors-0.1.0.dist-info/top_level.txt
