Metadata-Version: 2.0
Name: dataextractors
Version: 0.1.0
Summary: Extract pixels and metadata using shapefiles and georeferenced imagery.
Home-page: https://github.com/platformstories/dataextractors
Author: Nikki Aldeborgh
Author-email: nikki.aldeborgh@digitalglobe.com
License: MIT
Platform: UNKNOWN
Requires-Dist: Pillow (==2.6.0)
Requires-Dist: bumpversion
Requires-Dist: geoio (>=1.1.1)
Requires-Dist: geojson (>=1.3.2)
Requires-Dist: geojsontools (>=0.0.2)
Requires-Dist: numpy (>=1.12.0)
Requires-Dist: scipy
